wolf_core/__init__.py
wolf_core/api.py
wolf_core/application.py
wolf_core-2.0.1.dist-info/LICENSE
wolf_core-2.0.1.dist-info/METADATA
wolf_core-2.0.1.dist-info/WHEEL
wolf_core-2.0.1.dist-info/RECORD
